sidhulabs/__init__.py
sidhulabs/database/base_sql_model.py
sidhulabs/database/conn.py
sidhulabs/decorators.py
sidhulabs/elastic/client.py
sidhulabs/elastic/documents.py
sidhulabs/notifications.py
sidhulabs-2022.11.25.6.56.dist-info/LICENSE
sidhulabs-2022.11.25.6.56.dist-info/WHEEL
sidhulabs-2022.11.25.6.56.dist-info/METADATA
sidhulabs-2022.11.25.6.56.dist-info/RECORD
