Metadata-Version: 2.1
Name: sidhulabs
Version: 2022.11.25.6.56
Summary: Common Python utility functions
Author: Ashton Sidhu
Author-email: ashton.sidhu1994@gmail.com
Requires-Python: >=3.7,<4.0
Classifier: Programming Language :: Python :: 3
Classifier: Programming Language :: Python :: 3.10
Classifier: Programming Language :: Python :: 3.7
Classifier: Programming Language :: Python :: 3.8
Classifier: Programming Language :: Python :: 3.9
Requires-Dist: SQLAlchemy (>=1.4.31,<2.0.0)
Requires-Dist: elasticsearch (>=8,<9)
Requires-Dist: loguru (>=0.6.0,<0.7.0)
Requires-Dist: pyodbc (>=4.0.32,<5.0.0)
Requires-Dist: twilio (>=7.15.3,<8.0.0)
